{
  "id": "i-was-doing-all-right",
  "title": "I Was Doing All Right",
  "composers": [
    "George Gershwin"
  ],
  "year": 1937,
  "defaultKey": "G",
  "form": "A (1ª vuelta / 2ª vuelta) · B · A · 34 compases",
  "overview": "",
  "practiceFocus": [],
  "scaleHints": [],
  "realForm": {
    "sections": [
      {
        "id": "section-1",
        "label": "A · 1ª vuelta",
        "bars": "1-8",
        "timeSignature": "FOUR_FOUR",
        "measures": [
          {
            "bar": 1,
            "chords": [
              "GΔ7",
              "Abo7"
            ],
            "chordEvents": [
              {
                "display": "GΔ7",
                "load": "Gmaj7"
              },
              {
                "display": "Abo7",
                "load": "Abdim7"
              }
            ],
            "repeat": false
          },
          {
            "bar": 2,
            "chords": [
              "A-7",
              "D7"
            ],
            "chordEvents": [
              {
                "display": "A-7",
                "load": "Am7"
              },
              {
                "display": "D7",
                "load": "D7"
              }
            ],
            "repeat": false
          },
          {
            "bar": 3,
            "chords": [
              "GΔ7",
              "Abo7"
            ],
            "chordEvents": [
              {
                "display": "GΔ7",
                "load": "Gmaj7"
              },
              {
                "display": "Abo7",
                "load": "Abdim7"
              }
            ],
            "repeat": false
          },
          {
            "bar": 4,
            "chords": [
              "A-7",
              "D7"
            ],
            "chordEvents": [
              {
                "display": "A-7",
                "load": "Am7"
              },
              {
                "display": "D7",
                "load": "D7"
              }
            ],
            "repeat": false
          },
          {
            "bar": 5,
            "chords": [
              "G7"
            ],
            "chordEvents": [
              {
                "display": "G7",
                "load": "G7"
              }
            ],
            "repeat": false
          },
          {
            "bar": 6,
            "chords": [
              "CΔ7",
              "C-6"
            ],
            "chordEvents": [
              {
                "display": "CΔ7",
                "load": "Cmaj7"
              },
              {
                "display": "C-6",
                "load": "Cm6"
              }
            ],
            "repeat": false
          },
          {
            "bar": 7,
            "chords": [
              "GΔ7/D",
              "D7"
            ],
            "chordEvents": [
              {
                "display": "GΔ7/D",
                "load": "Gmaj7"
              },
              {
                "display": "D7",
                "load": "D7"
              }
            ],
            "repeat": false
          },
          {
            "bar": 8,
            "chords": [
              "GΔ7",
              "A-7",
              "D7"
            ],
            "chordEvents": [
              {
                "display": "GΔ7",
                "load": "Gmaj7"
              },
              {
                "display": "A-7",
                "load": "Am7"
              },
              {
                "display": "D7",
                "load": "D7"
              }
            ],
            "repeat": false
          }
        ]
      },
      {
        "id": "section-2",
        "label": "A · 2ª vuelta",
        "bars": "1-7, 9",
        "timeSignature": "FOUR_FOUR",
        "measures": [
          {
            "bar": 1,
            "chords": [
              "GΔ7",
              "Abo7"
            ],
            "chordEvents": [
              {
                "display": "GΔ7",
                "load": "Gmaj7"
              },
              {
                "display": "Abo7",
                "load": "Abdim7"
              }
            ],
            "repeat": false
          },
          {
            "bar": 2,
            "chords": [
              "A-7",
              "D7"
            ],
            "chordEvents": [
              {
                "display": "A-7",
                "load": "Am7"
              },
              {
                "display": "D7",
                "load": "D7"
              }
            ],
            "repeat": false
          },
          {
            "bar": 3,
            "chords": [
              "GΔ7",
              "Abo7"
            ],
            "chordEvents": [
              {
                "display": "GΔ7",
                "load": "Gmaj7"
              },
              {
                "display": "Abo7",
                "load": "Abdim7"
              }
            ],
            "repeat": false
          },
          {
            "bar": 4,
            "chords": [
              "A-7",
              "D7"
            ],
            "chordEvents": [
              {
                "display": "A-7",
                "load": "Am7"
              },
              {
                "display": "D7",
                "load": "D7"
              }
            ],
            "repeat": false
          },
          {
            "bar": 5,
            "chords": [
              "G7"
            ],
            "chordEvents": [
              {
                "display": "G7",
                "load": "G7"
              }
            ],
            "repeat": false
          },
          {
            "bar": 6,
            "chords": [
              "CΔ7",
              "C-6"
            ],
            "chordEvents": [
              {
                "display": "CΔ7",
                "load": "Cmaj7"
              },
              {
                "display": "C-6",
                "load": "Cm6"
              }
            ],
            "repeat": false
          },
          {
            "bar": 7,
            "chords": [
              "GΔ7/D",
              "D7"
            ],
            "chordEvents": [
              {
                "display": "GΔ7/D",
                "load": "Gmaj7"
              },
              {
                "display": "D7",
                "load": "D7"
              }
            ],
            "repeat": false
          },
          {
            "bar": 9,
            "chords": [
              "GΔ7",
              "B7"
            ],
            "chordEvents": [
              {
                "display": "GΔ7",
                "load": "Gmaj7"
              },
              {
                "display": "B7",
                "load": "B7"
              }
            ],
            "repeat": false
          }
        ]
      },
      {
        "id": "section-3",
        "label": "B",
        "bars": "10-17",
        "timeSignature": "FOUR_FOUR",
        "measures": [
          {
            "bar": 10,
            "chords": [
              "E6"
            ],
            "chordEvents": [
              {
                "display": "E6",
                "load": "E6"
              }
            ],
            "repeat": false
          },
          {
            "bar": 11,
            "chords": [
              "E6"
            ],
            "chordEvents": [
              {
                "display": "E6",
                "load": "E6"
              }
            ],
            "repeat": false
          },
          {
            "bar": 12,
            "chords": [
              "A7"
            ],
            "chordEvents": [
              {
                "display": "A7",
                "load": "A7"
              }
            ],
            "repeat": false
          },
          {
            "bar": 13,
            "chords": [
              "A7"
            ],
            "chordEvents": [
              {
                "display": "A7",
                "load": "A7"
              }
            ],
            "repeat": false
          },
          {
            "bar": 14,
            "chords": [
              "E6"
            ],
            "chordEvents": [
              {
                "display": "E6",
                "load": "E6"
              }
            ],
            "repeat": false
          },
          {
            "bar": 15,
            "chords": [
              "C#-7",
              "B6"
            ],
            "chordEvents": [
              {
                "display": "C#-7",
                "load": "C#m7"
              },
              {
                "display": "B6",
                "load": "B6"
              }
            ],
            "repeat": false
          },
          {
            "bar": 16,
            "chords": [
              "F#-7",
              "G#-7"
            ],
            "chordEvents": [
              {
                "display": "F#-7",
                "load": "F#m7"
              },
              {
                "display": "G#-7",
                "load": "G#m7"
              }
            ],
            "repeat": false
          },
          {
            "bar": 17,
            "chords": [
              "A-7",
              "Bbo7"
            ],
            "chordEvents": [
              {
                "display": "A-7",
                "load": "Am7"
              },
              {
                "display": "Bbo7",
                "load": "Bbdim7"
              }
            ],
            "repeat": false
          }
        ]
      },
      {
        "id": "section-4",
        "label": "A",
        "bars": "18-27",
        "timeSignature": "FOUR_FOUR",
        "measures": [
          {
            "bar": 18,
            "chords": [
              "GΔ7",
              "Abo7"
            ],
            "chordEvents": [
              {
                "display": "GΔ7",
                "load": "Gmaj7"
              },
              {
                "display": "Abo7",
                "load": "Abdim7"
              }
            ],
            "repeat": false
          },
          {
            "bar": 19,
            "chords": [
              "A-7",
              "D7"
            ],
            "chordEvents": [
              {
                "display": "A-7",
                "load": "Am7"
              },
              {
                "display": "D7",
                "load": "D7"
              }
            ],
            "repeat": false
          },
          {
            "bar": 20,
            "chords": [
              "GΔ7",
              "Abo7"
            ],
            "chordEvents": [
              {
                "display": "GΔ7",
                "load": "Gmaj7"
              },
              {
                "display": "Abo7",
                "load": "Abdim7"
              }
            ],
            "repeat": false
          },
          {
            "bar": 21,
            "chords": [
              "A-7",
              "D7"
            ],
            "chordEvents": [
              {
                "display": "A-7",
                "load": "Am7"
              },
              {
                "display": "D7",
                "load": "D7"
              }
            ],
            "repeat": false
          },
          {
            "bar": 22,
            "chords": [
              "G7"
            ],
            "chordEvents": [
              {
                "display": "G7",
                "load": "G7"
              }
            ],
            "repeat": false
          },
          {
            "bar": 23,
            "chords": [
              "CΔ7",
              "C-6"
            ],
            "chordEvents": [
              {
                "display": "CΔ7",
                "load": "Cmaj7"
              },
              {
                "display": "C-6",
                "load": "Cm6"
              }
            ],
            "repeat": false
          },
          {
            "bar": 24,
            "chords": [
              "GΔ7/D",
              "D7"
            ],
            "chordEvents": [
              {
                "display": "GΔ7/D",
                "load": "Gmaj7"
              },
              {
                "display": "D7",
                "load": "D7"
              }
            ],
            "repeat": false
          },
          {
            "bar": 25,
            "chords": [
              "A-7",
              "D7"
            ],
            "chordEvents": [
              {
                "display": "A-7",
                "load": "Am7"
              },
              {
                "display": "D7",
                "load": "D7"
              }
            ],
            "repeat": false
          },
          {
            "bar": 26,
            "chords": [
              "G6",
              "E7"
            ],
            "chordEvents": [
              {
                "display": "G6",
                "load": "G6"
              },
              {
                "display": "E7",
                "load": "E7"
              }
            ],
            "repeat": false
          },
          {
            "bar": 27,
            "chords": [
              "A-7",
              "D7"
            ],
            "chordEvents": [
              {
                "display": "A-7",
                "load": "Am7"
              },
              {
                "display": "D7",
                "load": "D7"
              }
            ],
            "repeat": false
          }
        ]
      }
    ]
  },
  "phrases": [
    {
      "section": "A · 1ª vuelta",
      "bars": "1-4",
      "label": "Tramo 1",
      "measures": [
        {
          "bar": 1,
          "repeat": false,
          "chordEvents": [
            {
              "display": "GΔ7",
              "load": "Gmaj7"
            },
            {
              "display": "Abo7",
              "load": "Abdim7"
            }
          ],
          "chords": [
            "GΔ7",
            "Abo7"
          ]
        },
        {
          "bar": 2,
          "repeat": false,
          "chordEvents": [
            {
              "display": "A-7",
              "load": "Am7"
            },
            {
              "display": "D7",
              "load": "D7"
            }
          ],
          "chords": [
            "A-7",
            "D7"
          ]
        },
        {
          "bar": 3,
          "repeat": false,
          "chordEvents": [
            {
              "display": "GΔ7",
              "load": "Gmaj7"
            },
            {
              "display": "Abo7",
              "load": "Abdim7"
            }
          ],
          "chords": [
            "GΔ7",
            "Abo7"
          ]
        },
        {
          "bar": 4,
          "repeat": false,
          "chordEvents": [
            {
              "display": "A-7",
              "load": "Am7"
            },
            {
              "display": "D7",
              "load": "D7"
            }
          ],
          "chords": [
            "A-7",
            "D7"
          ]
        }
      ]
    },
    {
      "section": "A · 1ª vuelta",
      "bars": "5-8",
      "label": "Tramo 2",
      "measures": [
        {
          "bar": 5,
          "repeat": false,
          "chordEvents": [
            {
              "display": "G7",
              "load": "G7"
            }
          ],
          "chords": [
            "G7"
          ]
        },
        {
          "bar": 6,
          "repeat": false,
          "chordEvents": [
            {
              "display": "CΔ7",
              "load": "Cmaj7"
            },
            {
              "display": "C-6",
              "load": "Cm6"
            }
          ],
          "chords": [
            "CΔ7",
            "C-6"
          ]
        },
        {
          "bar": 7,
          "repeat": false,
          "chordEvents": [
            {
              "display": "GΔ7/D",
              "load": "Gmaj7"
            },
            {
              "display": "D7",
              "load": "D7"
            }
          ],
          "chords": [
            "GΔ7/D",
            "D7"
          ]
        },
        {
          "bar": 8,
          "repeat": false,
          "chordEvents": [
            {
              "display": "GΔ7",
              "load": "Gmaj7"
            },
            {
              "display": "A-7",
              "load": "Am7"
            },
            {
              "display": "D7",
              "load": "D7"
            }
          ],
          "chords": [
            "GΔ7",
            "A-7",
            "D7"
          ]
        }
      ]
    },
    {
      "section": "A · 2ª vuelta",
      "bars": "1-4",
      "label": "Tramo 1",
      "measures": [
        {
          "bar": 1,
          "repeat": false,
          "chordEvents": [
            {
              "display": "GΔ7",
              "load": "Gmaj7"
            },
            {
              "display": "Abo7",
              "load": "Abdim7"
            }
          ],
          "chords": [
            "GΔ7",
            "Abo7"
          ]
        },
        {
          "bar": 2,
          "repeat": false,
          "chordEvents": [
            {
              "display": "A-7",
              "load": "Am7"
            },
            {
              "display": "D7",
              "load": "D7"
            }
          ],
          "chords": [
            "A-7",
            "D7"
          ]
        },
        {
          "bar": 3,
          "repeat": false,
          "chordEvents": [
            {
              "display": "GΔ7",
              "load": "Gmaj7"
            },
            {
              "display": "Abo7",
              "load": "Abdim7"
            }
          ],
          "chords": [
            "GΔ7",
            "Abo7"
          ]
        },
        {
          "bar": 4,
          "repeat": false,
          "chordEvents": [
            {
              "display": "A-7",
              "load": "Am7"
            },
            {
              "display": "D7",
              "load": "D7"
            }
          ],
          "chords": [
            "A-7",
            "D7"
          ]
        }
      ]
    },
    {
      "section": "A · 2ª vuelta",
      "bars": "5-7, 9",
      "label": "Tramo 2",
      "measures": [
        {
          "bar": 5,
          "repeat": false,
          "chordEvents": [
            {
              "display": "G7",
              "load": "G7"
            }
          ],
          "chords": [
            "G7"
          ]
        },
        {
          "bar": 6,
          "repeat": false,
          "chordEvents": [
            {
              "display": "CΔ7",
              "load": "Cmaj7"
            },
            {
              "display": "C-6",
              "load": "Cm6"
            }
          ],
          "chords": [
            "CΔ7",
            "C-6"
          ]
        },
        {
          "bar": 7,
          "repeat": false,
          "chordEvents": [
            {
              "display": "GΔ7/D",
              "load": "Gmaj7"
            },
            {
              "display": "D7",
              "load": "D7"
            }
          ],
          "chords": [
            "GΔ7/D",
            "D7"
          ]
        },
        {
          "bar": 9,
          "repeat": false,
          "chordEvents": [
            {
              "display": "GΔ7",
              "load": "Gmaj7"
            },
            {
              "display": "B7",
              "load": "B7"
            }
          ],
          "chords": [
            "GΔ7",
            "B7"
          ]
        }
      ]
    },
    {
      "section": "B",
      "bars": "10-13",
      "label": "Tramo 1",
      "measures": [
        {
          "bar": 10,
          "repeat": false,
          "chordEvents": [
            {
              "display": "E6",
              "load": "E6"
            }
          ],
          "chords": [
            "E6"
          ]
        },
        {
          "bar": 11,
          "repeat": false,
          "chordEvents": [
            {
              "display": "E6",
              "load": "E6"
            }
          ],
          "chords": [
            "E6"
          ]
        },
        {
          "bar": 12,
          "repeat": false,
          "chordEvents": [
            {
              "display": "A7",
              "load": "A7"
            }
          ],
          "chords": [
            "A7"
          ]
        },
        {
          "bar": 13,
          "repeat": false,
          "chordEvents": [
            {
              "display": "A7",
              "load": "A7"
            }
          ],
          "chords": [
            "A7"
          ]
        }
      ]
    },
    {
      "section": "B",
      "bars": "14-17",
      "label": "Tramo 2",
      "measures": [
        {
          "bar": 14,
          "repeat": false,
          "chordEvents": [
            {
              "display": "E6",
              "load": "E6"
            }
          ],
          "chords": [
            "E6"
          ]
        },
        {
          "bar": 15,
          "repeat": false,
          "chordEvents": [
            {
              "display": "C#-7",
              "load": "C#m7"
            },
            {
              "display": "B6",
              "load": "B6"
            }
          ],
          "chords": [
            "C#-7",
            "B6"
          ]
        },
        {
          "bar": 16,
          "repeat": false,
          "chordEvents": [
            {
              "display": "F#-7",
              "load": "F#m7"
            },
            {
              "display": "G#-7",
              "load": "G#m7"
            }
          ],
          "chords": [
            "F#-7",
            "G#-7"
          ]
        },
        {
          "bar": 17,
          "repeat": false,
          "chordEvents": [
            {
              "display": "A-7",
              "load": "Am7"
            },
            {
              "display": "Bbo7",
              "load": "Bbdim7"
            }
          ],
          "chords": [
            "A-7",
            "Bbo7"
          ]
        }
      ]
    },
    {
      "section": "A",
      "bars": "18-21",
      "label": "Tramo 1",
      "measures": [
        {
          "bar": 18,
          "repeat": false,
          "chordEvents": [
            {
              "display": "GΔ7",
              "load": "Gmaj7"
            },
            {
              "display": "Abo7",
              "load": "Abdim7"
            }
          ],
          "chords": [
            "GΔ7",
            "Abo7"
          ]
        },
        {
          "bar": 19,
          "repeat": false,
          "chordEvents": [
            {
              "display": "A-7",
              "load": "Am7"
            },
            {
              "display": "D7",
              "load": "D7"
            }
          ],
          "chords": [
            "A-7",
            "D7"
          ]
        },
        {
          "bar": 20,
          "repeat": false,
          "chordEvents": [
            {
              "display": "GΔ7",
              "load": "Gmaj7"
            },
            {
              "display": "Abo7",
              "load": "Abdim7"
            }
          ],
          "chords": [
            "GΔ7",
            "Abo7"
          ]
        },
        {
          "bar": 21,
          "repeat": false,
          "chordEvents": [
            {
              "display": "A-7",
              "load": "Am7"
            },
            {
              "display": "D7",
              "load": "D7"
            }
          ],
          "chords": [
            "A-7",
            "D7"
          ]
        }
      ]
    },
    {
      "section": "A",
      "bars": "22-25",
      "label": "Tramo 2",
      "measures": [
        {
          "bar": 22,
          "repeat": false,
          "chordEvents": [
            {
              "display": "G7",
              "load": "G7"
            }
          ],
          "chords": [
            "G7"
          ]
        },
        {
          "bar": 23,
          "repeat": false,
          "chordEvents": [
            {
              "display": "CΔ7",
              "load": "Cmaj7"
            },
            {
              "display": "C-6",
              "load": "Cm6"
            }
          ],
          "chords": [
            "CΔ7",
            "C-6"
          ]
        },
        {
          "bar": 24,
          "repeat": false,
          "chordEvents": [
            {
              "display": "GΔ7/D",
              "load": "Gmaj7"
            },
            {
              "display": "D7",
              "load": "D7"
            }
          ],
          "chords": [
            "GΔ7/D",
            "D7"
          ]
        },
        {
          "bar": 25,
          "repeat": false,
          "chordEvents": [
            {
              "display": "A-7",
              "load": "Am7"
            },
            {
              "display": "D7",
              "load": "D7"
            }
          ],
          "chords": [
            "A-7",
            "D7"
          ]
        }
      ]
    },
    {
      "section": "A",
      "bars": "26-27",
      "label": "Tramo 3",
      "measures": [
        {
          "bar": 26,
          "repeat": false,
          "chordEvents": [
            {
              "display": "G6",
              "load": "G6"
            },
            {
              "display": "E7",
              "load": "E7"
            }
          ],
          "chords": [
            "G6",
            "E7"
          ]
        },
        {
          "bar": 27,
          "repeat": false,
          "chordEvents": [
            {
              "display": "A-7",
              "load": "Am7"
            },
            {
              "display": "D7",
              "load": "D7"
            }
          ],
          "chords": [
            "A-7",
            "D7"
          ]
        }
      ]
    }
  ]
}
